{
  "passed": true,
  "checks": {
    "length": "pass",
    "citations": "pass",
    "forward_refs": "pass",
    "faithfulness": "pass",
    "structure": "pass",
    "tone": "pass",
    "diagram_embed": "pass"
  },
  "verdict": "PASS (re-validation after mermaid diagram embed). DIAGRAM EMBED: a fenced ```mermaid block is present (L75-L109) inserted between Key Concepts and Worked Example, preceded by a prose caption (L73: 'The precedence ladder at a glance.' with a one-sentence explanation that top binds first, bottom binds last, and parentheses override). The embedded block content (L76-L108) is byte-for-byte consistent with the already-critic-passed standalone artifacts/diagram.mmd (title 'Operator precedence ladder (highest binds first)', flowchart TB, nodes PAREN->POW->NEG->MUL->ADD->CMP->LOGIC, same classDefs); sidecar embeds_diagram=true. LENGTH: mermaid fenced block (L75-L109) EXCLUDED from word count per deep-band rule; prose word_count remains ~1963 (sidecar reports 1963) within deep band 1800-2200; the added caption (~40 words) keeps prose comfortably inside band; ~9.8 min at 200 wpm (within 9-11); reading-aloud minutes also in range. STRUCTURE: first line still the H1 '# Operators & Expressions' with no YAML frontmatter; exactly the six required sections in order (Overview L3, Key Concepts L7, Worked Example L111, In Practice L142, Key Takeaways L151, References L159) -- the embed lives inside Key Concepts and adds no new heading. CITATIONS: [1] Real Python (realpython.com/python-operators-expressions), [2] docs.python.org/3/reference/expressions.html, [3] GeeksforGeeks python/python-operators all still cited inline and listed in bibliography (L161-163); no orphan markers, no orphan bibliography entries; caption/diagram introduce no new uncited claims. FORWARD REFERENCES: caption and diagram teach only operator precedence ordering, an in-scope 1.3 concept traceable to corpus L250-262; no 1.4 material introduced (no int()/float()/str()/bool() conversion functions, no f-strings, no string indexing/slicing, no if/while control flow, no type hints, no match-case); truthiness, comparison, logical, and short-circuit remain in-scope. FAITHFULNESS: re-sampled including the new content -- precedence ladder ordering PAREN/**/unary-minus/(*,/,//,%)/(+,-)/comparisons/(not,and,or) matches corpus ladder table (L252-262); caption claim 'work down this ladder or add parentheses to override' traces to corpus L328,L342; plus prior 11 assertions (-7//2=-4 L141, -7%2=1 L198/L209, -2**2=-4 vs (-2)**2=4 L276-280, left-associativity L300-314, falsy list L558-564, not>and>or L481, 'cat'=='Cat' False L392-405, chained 1<x<10 L423-440, short-circuit L517-536, (a//b)*b+(a%b) L146, worked-example output verbatim L717-722) -- all trace to topic_corpus.md, 0 unsupported. TONE: caption is plainspoken and beginner-facing, consistent with the surrounding prose and siblings 1.1/1.2; no academic hedging; sentence lengths controlled. Prose otherwise unchanged from the prior passing revision.",
  "at": "2026-07-13T00:00:00Z"
}
